codexprime/__init__.py
codexprime_aditya-0.0.1.dist-info/METADATA
codexprime_aditya-0.0.1.dist-info/WHEEL
codexprime_aditya-0.0.1.dist-info/top_level.txt
codexprime_aditya-0.0.1.dist-info/RECORD
