Metadata-Version: 2.1
Name: codexprime-aditya
Version: 0.0.1
Requires-Dist: requests
